CyclicGAN/__init__.py
CyclicGAN/config.py
CyclicGAN/cyclicGAN.py
CyclicGAN/discriminator.py
CyclicGAN/generator.py
CyclicGAN/loss.py
cyclicgan-0.0.2.dist-info/LICENSE
cyclicgan-0.0.2.dist-info/METADATA
cyclicgan-0.0.2.dist-info/WHEEL
cyclicgan-0.0.2.dist-info/top_level.txt
cyclicgan-0.0.2.dist-info/RECORD
