Metadata-Version: 2.1
Name: cyclicgan
Version: 0.0.2
Summary: An API implementation of CyclicGAN network.
Home-page: https://github.com/sarthakforwet/CyclicGAN_Implementation
Author: Sarthak Khandelwal
Author-email: sarthakkhandelwal032000@gmail.com
License: UNKNOWN
Platform: UNKNOWN
Requires-Python: >=3.6
